ec_number_prediction/__init__.py
ec_number_prediction/_utils.py
ec_number_prediction/ecpick.py
ec_number_prediction/enumerators.py
ec_number_prediction/labels_names.pkl
ec_number_prediction/labels_names_all_data.pkl
ec_number_prediction/predictions.py
ec_number_prediction/run_data_processing_pipeline.py
ec_number_prediction/data_processing_pipeline/__init__.py
ec_number_prediction/data_processing_pipeline/download_uniprot.py
ec_number_prediction/data_processing_pipeline/enrichment_with_trembl.py
ec_number_prediction/data_processing_pipeline/filter_uniref.py
ec_number_prediction/data_processing_pipeline/multi_label_binarizer.py
ec_number_prediction/data_processing_pipeline/n_classes_removal.py
ec_number_prediction/data_processing_pipeline/scrape_uniprot.py
ec_number_prediction/data_processing_pipeline/split.py
ec_number_prediction/data_processing_pipeline/underrepresented_labels_removal.py
ec_number_prediction/data_processing_pipeline/uniprot_xml_parser.py
ec_number_prediction/data_processing_pipeline/uniref_xml_parser.py
ec_number_prediction/feature_extraction/__init__.py
ec_number_prediction/feature_extraction/generate_features.py
ec_number_prediction/train_models/__init__.py
ec_number_prediction/train_models/optimize_dnn.py
ec_number_prediction/train_models/pipeline_runner.py
ec_number_prediction/train_models/train_baselines.py
ec_number_prediction/train_models/train_deep_ec.py
ec_number_prediction/train_models/train_dspace.py
ec_number_prediction-0.0.5.dist-info/LICENSE
ec_number_prediction-0.0.5.dist-info/METADATA
ec_number_prediction-0.0.5.dist-info/WHEEL
ec_number_prediction-0.0.5.dist-info/dependency_links.txt
ec_number_prediction-0.0.5.dist-info/top_level.txt
ec_number_prediction-0.0.5.dist-info/RECORD
