Metadata-Version: 2.1
Name: ec_number_prediction
Version: 0.0.5
Summary: ec_number_prediction
Author: Joao Capela
License: MIT
Keywords: plants,secondary metabolism
Platform: unix
Platform: linux
Platform: osx
Platform: cygwin
Platform: win32
Classifier: Programming Language :: Python :: 3
Classifier: Programming Language :: Python :: 3 :: Only
Classifier: Programming Language :: Python :: 3.9
Classifier: Programming Language :: Python :: 3.10
Requires-Python: >=3.9
License-File: LICENSE
Requires-Dist: plants-sm ==0.0.2
Requires-Dist: luigi
Requires-Dist: scikit-multilearn
Requires-Dist: matplotlib-venn
Provides-Extra: testing
Requires-Dist: pytest >=7.1.1 ; extra == 'testing'
Requires-Dist: pytest-cov >=3.0.0 ; extra == 'testing'
Requires-Dist: mypy >=0.942 ; extra == 'testing'
Requires-Dist: flake8 >=4.0.1 ; extra == 'testing'
Requires-Dist: tox >=3.25.0 ; extra == 'testing'
